product_crawler/__init__.py
product_crawler/config.py
product_crawler/crawler/__init__.py
product_crawler/crawler/crawler.py
product_crawler/crawler/parser.py
product_crawler/helpers/__init__.py
product_crawler/helpers/fetch_website_body.py
product_crawler/main.py
product_crawler/scraper/__init__.py
product_crawler/scraper/scraper.py
product_crawler/storage/__init__.py
product_crawler/storage/storage.py
product_crawler/viewer/__init__.py
product_crawler/viewer/viewer.py
product_crawler-0.2.2.dist-info/entry_points.txt
product_crawler-0.2.2.dist-info/WHEEL
product_crawler-0.2.2.dist-info/METADATA
product_crawler-0.2.2.dist-info/RECORD
